dsf_label_sdk/__init__.py
dsf_label_sdk/client.py
dsf_label_sdk/exceptions.py
dsf_label_sdk/models.py
dsf_label_sdk-1.3.14.dist-info/METADATA
dsf_label_sdk-1.3.14.dist-info/WHEEL
dsf_label_sdk-1.3.14.dist-info/top_level.txt
dsf_label_sdk-1.3.14.dist-info/RECORD
