Metadata-Version: 2.4
Name: dsf-label-sdk
Version: 1.3.14
Summary: Professional SDK for DSF Label Adaptive Formula API
Home-page: https://github.com/jaimeajl/dsf-label-sdk
Author: Jaime Alexander Jimenez
Author-email: contacto@dsfuptech.cloud
License: Proprietary - DSF Label SDK © 2025 Jaime Alexander Jimenez (operating as Uptech)
Project-URL: Bug Tracker, https://github.com/jaimeajl/dsf-label-sdk/issues
Project-URL: Documentation, https://docs.jaimeajl.com/dsf-label-sdk
Project-URL: Source Code, https://github.com/jaimeajl/dsf-label-sdk
Keywords: dsf label adaptive formula evaluation api sdk
Classifier: Development Status :: 5 - Production/Stable
Classifier: Intended Audience :: Developers
Classifier: Topic :: Software Development :: Libraries :: Python Modules
Classifier: License :: Other/Proprietary License
Classifier: Programming Language :: Python :: 3
Classifier: Programming Language :: Python :: 3.7
Classifier: Programming Language :: Python :: 3.8
Classifier: Programming Language :: Python :: 3.9
Classifier: Programming Language :: Python :: 3.10
Classifier: Programming Language :: Python :: 3.11
Requires-Python: >=3.7
Requires-Dist: requests>=2.25.0
Provides-Extra: dev
Requires-Dist: pytest>=6.0; extra == "dev"
Requires-Dist: pytest-cov>=2.0; extra == "dev"
Requires-Dist: black>=21.0; extra == "dev"
Requires-Dist: flake8>=3.9; extra == "dev"
Requires-Dist: mypy>=0.900; extra == "dev"
Dynamic: author
Dynamic: author-email
Dynamic: classifier
Dynamic: description
Dynamic: description-content-type
Dynamic: home-page
Dynamic: keywords
Dynamic: license
Dynamic: project-url
Dynamic: provides-extra
Dynamic: requires-dist
Dynamic: requires-python
Dynamic: summary
